{
    "apiVersion": "v1",
    "kind": "Namespace",
    "metadata": {
        "annotations": {
            "kubectl.kubernetes.io/last-applied-configuration": "{\"apiVersion\":\"v1\",\"kind\":\"Namespace\",\"metadata\":{\"annotations\":{},\"labels\":{\"app.kubernetes.io/instance\":\"ingress-nginx\",\"app.kubernetes.io/name\":\"ingress-nginx\"},\"name\":\"ingress-nginx\"}}\n"
        },
        "creationTimestamp": "2026-04-14T17:12:48Z",
        "deletionTimestamp": "2026-04-14T17:15:50Z",
        "labels": {
            "app.kubernetes.io/instance": "ingress-nginx",
            "app.kubernetes.io/name": "ingress-nginx",
            "kubernetes.io/metadata.name": "ingress-nginx"
        },
        "name": "ingress-nginx",
        "resourceVersion": "6413",
        "uid": "09d4aff7-7f9f-4ac8-8f62-09bb0f75f29f"
    },
    "spec": {
        "finalizers": [
            "kubernetes"
        ]
    },
    "status": {
        "conditions": [
            {
                "lastTransitionTime": "2026-04-14T17:15:55Z",
                "message": "All resources successfully discovered",
                "reason": "ResourcesDiscovered",
                "status": "False",
                "type": "NamespaceDeletionDiscoveryFailure"
            },
            {
                "lastTransitionTime": "2026-04-14T17:15:55Z",
                "message": "All legacy kube types successfully parsed",
                "reason": "ParsedGroupVersions",
                "status": "False",
                "type": "NamespaceDeletionGroupVersionParsingFailure"
            },
            {
                "lastTransitionTime": "2026-04-14T17:15:55Z",
                "message": "All content successfully deleted, may be waiting on finalization",
                "reason": "ContentDeleted",
                "status": "False",
                "type": "NamespaceDeletionContentFailure"
            },
            {
                "lastTransitionTime": "2026-04-14T17:15:55Z",
                "message": "All content successfully removed",
                "reason": "ContentRemoved",
                "status": "False",
                "type": "NamespaceContentRemaining"
            },
            {
                "lastTransitionTime": "2026-04-14T17:15:55Z",
                "message": "All content-preserving finalizers finished",
                "reason": "ContentHasNoFinalizers",
                "status": "False",
                "type": "NamespaceFinalizersRemaining"
            }
        ],
        "phase": "Terminating"
    }
}
